{
    "Abaza": [
        "UD_Abaza-ATB"
    ],
    "Afrikaans": [
        "UD_Afrikaans-AfriBooms"
    ],
    "Akkadian": [
        "UD_Akkadian-PISANDUB",
        "UD_Akkadian-RIAO"
    ],
    "Akuntsu": [
        "UD_Akuntsu-TuDeT"
    ],
    "Albanian": [
        "UD_Albanian-TSA"
    ],
    "Amharic": [
        "UD_Amharic-ATT"
    ],
    "Ancient_Greek": [
        "UD_Ancient_Greek-PROIEL",
        "UD_Ancient_Greek-PTNK",
        "UD_Ancient_Greek-Perseus"
    ],
    "Ancient_Hebrew": [
        "UD_Ancient_Hebrew-PTNK"
    ],
    "Apurina": [
        "UD_Apurina-UFPA"
    ],
    "Arabic": [
        "UD_Arabic-NYUAD",
        "UD_Arabic-PADT",
        "UD_Arabic-PUD"
    ],
    "Armenian": [
        "UD_Armenian-ArmTDP",
        "UD_Armenian-BSUT"
    ],
    "Assyrian": [
        "UD_Assyrian-AS"
    ],
    "Bambara": [
        "UD_Bambara-CRB"
    ],
    "Basque": [
        "UD_Basque-BDT"
    ],
    "Beja": [
        "UD_Beja-NSC"
    ],
    "Belarusian": [
        "UD_Belarusian-HSE"
    ],
    "Bengali": [
        "UD_Bengali-BRU"
    ],
    "Bhojpuri": [
        "UD_Bhojpuri-BHTB"
    ],
    "Bororo": [
        "UD_Bororo-BDT"
    ],
    "Breton": [
        "UD_Breton-KEB"
    ],
    "Bulgarian": [
        "UD_Bulgarian-BTB"
    ],
    "Buryat": [
        "UD_Buryat-BDT"
    ],
    "Cantonese": [
        "UD_Cantonese-HK"
    ],
    "Catalan": [
        "UD_Catalan-AnCora"
    ],
    "Cebuano": [
        "UD_Cebuano-GJA"
    ],
    "Chinese": [
        "UD_Chinese-Beginner",
        "UD_Chinese-CFL",
        "UD_Chinese-GSD",
        "UD_Chinese-GSDSimp",
        "UD_Chinese-HK",
        "UD_Chinese-PUD",
        "UD_Chinese-PatentChar"
    ],
    "Chukchi": [
        "UD_Chukchi-HSE"
    ],
    "Classical_Armenian": [
        "UD_Classical_Armenian-CAVaL"
    ],
    "Classical_Chinese": [
        "UD_Classical_Chinese-Kyoto"
    ],
    "Coptic": [
        "UD_Coptic-Scriptorium"
    ],
    "Croatian": [
        "UD_Croatian-SET"
    ],
    "Czech": [
        "UD_Czech-CAC",
        "UD_Czech-CLTT",
        "UD_Czech-FicTree",
        "UD_Czech-PDT",
        "UD_Czech-PUD",
        "UD_Czech-Poetry"
    ],
    "Danish": [
        "UD_Danish-DDT"
    ],
    "Dutch": [
        "UD_Dutch-Alpino",
        "UD_Dutch-LassySmall"
    ],
    "English": [
        "UD_English-Atis",
        "UD_English-ESLSpok",
        "UD_English-EWT",
        "UD_English-GENTLE",
        "UD_English-GUM",
        "UD_English-GUMReddit",
        "UD_English-LinES",
        "UD_English-PUD",
        "UD_English-ParTUT",
        "UD_English-Pronouns"
    ],
    "Erzya": [
        "UD_Erzya-JR"
    ],
    "Estonian": [
        "UD_Estonian-EDT",
        "UD_Estonian-EWT"
    ],
    "Faroese": [
        "UD_Faroese-FarPaHC",
        "UD_Faroese-OFT"
    ],
    "Finnish": [
        "UD_Finnish-FTB",
        "UD_Finnish-OOD",
        "UD_Finnish-PUD",
        "UD_Finnish-TDT"
    ],
    "French": [
        "UD_French-FQB",
        "UD_French-GSD",
        "UD_French-PUD",
        "UD_French-ParTUT",
        "UD_French-ParisStories",
        "UD_French-Rhapsodie",
        "UD_French-Sequoia"
    ],
    "Frisian_Dutch": [
        "UD_Frisian_Dutch-Fame"
    ],
    "Galician": [
        "UD_Galician-CTG",
        "UD_Galician-TreeGal"
    ],
    "Georgian": [
        "UD_Georgian-GLC"
    ],
    "German": [
        "UD_German-GSD",
        "UD_German-HDT",
        "UD_German-LIT",
        "UD_German-PUD"
    ],
    "Gheg": [
        "UD_Gheg-GPS"
    ],
    "Gothic": [
        "UD_Gothic-PROIEL"
    ],
    "Greek": [
        "UD_Greek-GDT",
        "UD_Greek-GUD"
    ],
    "Guajajara": [
        "UD_Guajajara-TuDeT"
    ],
    "Guarani": [
        "UD_Guarani-OldTuDeT"
    ],
    "Haitian_Creole": [
        "UD_Haitian_Creole-Autogramm"
    ],
    "Hebrew": [
        "UD_Hebrew-HTB",
        "UD_Hebrew-IAHLTwiki"
    ],
    "Highland_Puebla_Nahuatl": [
        "UD_Highland_Puebla_Nahuatl-ITML"
    ],
    "Hindi": [
        "UD_Hindi-HDTB",
        "UD_Hindi-PUD"
    ],
    "Hittite": [
        "UD_Hittite-HitTB"
    ],
    "Hungarian": [
        "UD_Hungarian-Szeged"
    ],
    "Icelandic": [
        "UD_Icelandic-GC",
        "UD_Icelandic-IcePaHC",
        "UD_Icelandic-Modern",
        "UD_Icelandic-PUD"
    ],
    "Indonesian": [
        "UD_Indonesian-CSUI",
        "UD_Indonesian-GSD",
        "UD_Indonesian-PUD"
    ],
    "Irish": [
        "UD_Irish-Cadhan",
        "UD_Irish-IDT",
        "UD_Irish-TwittIrish"
    ],
    "Italian": [
        "UD_Italian-ISDT",
        "UD_Italian-MarkIT",
        "UD_Italian-Old",
        "UD_Italian-PUD",
        "UD_Italian-ParTUT",
        "UD_Italian-ParlaMint",
        "UD_Italian-PoSTWITA",
        "UD_Italian-TWITTIRO",
        "UD_Italian-VIT",
        "UD_Italian-Valico"
    ],
    "Japanese": [
        "UD_Japanese-BCCWJ",
        "UD_Japanese-BCCWJLUW",
        "UD_Japanese-GSD",
        "UD_Japanese-GSDLUW",
        "UD_Japanese-PUD",
        "UD_Japanese-PUDLUW"
    ],
    "Javanese": [
        "UD_Javanese-CSUI"
    ],
    "Kaapor": [
        "UD_Kaapor-TuDeT"
    ],
    "Kangri": [
        "UD_Kangri-KDTB"
    ],
    "Karelian": [
        "UD_Karelian-KKPP"
    ],
    "Karo": [
        "UD_Karo-TuDeT"
    ],
    "Kazakh": [
        "UD_Kazakh-KTB"
    ],
    "Khunsari": [
        "UD_Khunsari-AHA"
    ],
    "Kiche": [
        "UD_Kiche-IU"
    ],
    "Komi_Permyak": [
        "UD_Komi_Permyak-UH"
    ],
    "Komi_Zyrian": [
        "UD_Komi_Zyrian-IKDP",
        "UD_Komi_Zyrian-Lattice"
    ],
    "Korean": [
        "UD_Korean-GSD",
        "UD_Korean-Kaist",
        "UD_Korean-PUD"
    ],
    "Kurmanji": [
        "UD_Kurmanji-MG"
    ],
    "Kyrgyz": [
        "UD_Kyrgyz-KTMU"
    ],
    "Latin": [
        "UD_Latin-ITTB",
        "UD_Latin-LLCT",
        "UD_Latin-PROIEL",
        "UD_Latin-Perseus",
        "UD_Latin-UDante"
    ],
    "Latvian": [
        "UD_Latvian-LVTB"
    ],
    "Ligurian": [
        "UD_Ligurian-GLT"
    ],
    "Lithuanian": [
        "UD_Lithuanian-ALKSNIS",
        "UD_Lithuanian-HSE"
    ],
    "Livvi": [
        "UD_Livvi-KKPP"
    ],
    "Low_Saxon": [
        "UD_Low_Saxon-LSDC"
    ],
    "Macedonian": [
        "UD_Macedonian-MTB"
    ],
    "Madi": [
        "UD_Madi-Jarawara"
    ],
    "Maghrebi_Arabic_French": [
        "UD_Maghrebi_Arabic_French-Arabizi"
    ],
    "Makurap": [
        "UD_Makurap-TuDeT"
    ],
    "Malayalam": [
        "UD_Malayalam-UFAL"
    ],
    "Maltese": [
        "UD_Maltese-MUDT"
    ],
    "Manx": [
        "UD_Manx-Cadhan"
    ],
    "Marathi": [
        "UD_Marathi-UFAL"
    ],
    "Mbya_Guarani": [
        "UD_Mbya_Guarani-Dooley",
        "UD_Mbya_Guarani-Thomas"
    ],
    "Middle_French": [
        "UD_Middle_French-PROFITEROLE"
    ],
    "Moksha": [
        "UD_Moksha-JR"
    ],
    "Munduruku": [
        "UD_Munduruku-TuDeT"
    ],
    "Naija": [
        "UD_Naija-NSC"
    ],
    "Nayini": [
        "UD_Nayini-AHA"
    ],
    "Neapolitan": [
        "UD_Neapolitan-RB"
    ],
    "Nheengatu": [
        "UD_Nheengatu-CompLin"
    ],
    "North_Sami": [
        "UD_North_Sami-Giella"
    ],
    "Norwegian": [
        "UD_Norwegian-Bokmaal",
        "UD_Norwegian-Nynorsk"
    ],
    "Old_Church_Slavonic": [
        "UD_Old_Church_Slavonic-PROIEL"
    ],
    "Old_East_Slavic": [
        "UD_Old_East_Slavic-Birchbark",
        "UD_Old_East_Slavic-RNC",
        "UD_Old_East_Slavic-Ruthenian",
        "UD_Old_East_Slavic-TOROT"
    ],
    "Old_French": [
        "UD_Old_French-PROFITEROLE"
    ],
    "Old_Irish": [
        "UD_Old_Irish-DipSGG",
        "UD_Old_Irish-DipWBG"
    ],
    "Old_Turkish": [
        "UD_Old_Turkish-Clausal"
    ],
    "Persian": [
        "UD_Persian-PerDT",
        "UD_Persian-Seraji"
    ],
    "Polish": [
        "UD_Polish-LFG",
        "UD_Polish-PDB",
        "UD_Polish-PUD"
    ],
    "Pomak": [
        "UD_Pomak-Philotis"
    ],
    "Portuguese": [
        "UD_Portuguese-Bosque",
        "UD_Portuguese-CINTIL",
        "UD_Portuguese-GSD",
        "UD_Portuguese-PUD",
        "UD_Portuguese-PetroGold",
        "UD_Portuguese-Porttinari"
    ],
    "Romanian": [
        "UD_Romanian-ArT",
        "UD_Romanian-Nonstandard",
        "UD_Romanian-RRT",
        "UD_Romanian-SiMoNERo"
    ],
    "Russian": [
        "UD_Russian-GSD",
        "UD_Russian-PUD",
        "UD_Russian-Poetry",
        "UD_Russian-SynTagRus",
        "UD_Russian-Taiga"
    ],
    "Sanskrit": [
        "UD_Sanskrit-UFAL",
        "UD_Sanskrit-Vedic"
    ],
    "Scottish_Gaelic": [
        "UD_Scottish_Gaelic-ARCOSG"
    ],
    "Serbian": [
        "UD_Serbian-SET"
    ],
    "Sinhala": [
        "UD_Sinhala-STB"
    ],
    "Skolt_Sami": [
        "UD_Skolt_Sami-Giellagas"
    ],
    "Slovak": [
        "UD_Slovak-SNK"
    ],
    "Slovenian": [
        "UD_Slovenian-SSJ",
        "UD_Slovenian-SST"
    ],
    "Soi": [
        "UD_Soi-AHA"
    ],
    "South_Levantine_Arabic": [
        "UD_South_Levantine_Arabic-MADAR"
    ],
    "Spanish": [
        "UD_Spanish-AnCora",
        "UD_Spanish-GSD",
        "UD_Spanish-PUD"
    ],
    "Swedish": [
        "UD_Swedish-LinES",
        "UD_Swedish-PUD",
        "UD_Swedish-Talbanken"
    ],
    "Swedish_Sign_Language": [
        "UD_Swedish_Sign_Language-SSLC"
    ],
    "Swiss_German": [
        "UD_Swiss_German-UZH"
    ],
    "Tagalog": [
        "UD_Tagalog-TRG",
        "UD_Tagalog-Ugnayan"
    ],
    "Tamil": [
        "UD_Tamil-MWTT",
        "UD_Tamil-TTB"
    ],
    "Tatar": [
        "UD_Tatar-NMCTT"
    ],
    "Teko": [
        "UD_Teko-TuDeT"
    ],
    "Telugu": [
        "UD_Telugu-MTG"
    ],
    "Thai": [
        "UD_Thai-PUD"
    ],
    "Tupinamba": [
        "UD_Tupinamba-TuDeT"
    ],
    "Turkish": [
        "UD_Turkish-Atis",
        "UD_Turkish-BOUN",
        "UD_Turkish-FrameNet",
        "UD_Turkish-GB",
        "UD_Turkish-IMST",
        "UD_Turkish-Kenet",
        "UD_Turkish-PUD",
        "UD_Turkish-Penn",
        "UD_Turkish-Tourism"
    ],
    "Turkish_German": [
        "UD_Turkish_German-SAGT"
    ],
    "Ukrainian": [
        "UD_Ukrainian-IU"
    ],
    "Umbrian": [
        "UD_Umbrian-IKUVINA"
    ],
    "Upper_Sorbian": [
        "UD_Upper_Sorbian-UFAL"
    ],
    "Urdu": [
        "UD_Urdu-UDTB"
    ],
    "Uyghur": [
        "UD_Uyghur-UDT"
    ],
    "Veps": [
        "UD_Veps-VWT"
    ],
    "Vietnamese": [
        "UD_Vietnamese-VTB"
    ],
    "Warlpiri": [
        "UD_Warlpiri-UFAL"
    ],
    "Welsh": [
        "UD_Welsh-CCG"
    ],
    "Western_Armenian": [
        "UD_Western_Armenian-ArmTDP"
    ],
    "Western_Sierra_Puebla_Nahuatl": [
        "UD_Western_Sierra_Puebla_Nahuatl-ITML"
    ],
    "Wolof": [
        "UD_Wolof-WTB"
    ],
    "Xavante": [
        "UD_Xavante-XDT"
    ],
    "Xibe": [
        "UD_Xibe-XDT"
    ],
    "Yakut": [
        "UD_Yakut-YKTDT"
    ],
    "Yoruba": [
        "UD_Yoruba-YTB"
    ],
    "Yupik": [
        "UD_Yupik-SLI"
    ],
    "Zaar": [
        "UD_Zaar-Autogramm"
    ]
}